sparse_pls/__init__.py
sparse_pls/model.py
sparse_pls/preprocessing.py
tests/__init__.py
tests/test_model.py
sparse_pls-0.1.2.dist-info/LICENSE
sparse_pls-0.1.2.dist-info/METADATA
sparse_pls-0.1.2.dist-info/WHEEL
sparse_pls-0.1.2.dist-info/top_level.txt
sparse_pls-0.1.2.dist-info/RECORD
