Metadata-Version: 2.2
Name: sparse_pls
Version: 0.1.2
Summary: Sparse Partial Least Squares (Sparse PLS) Regression
Home-page: https://github.com/yajeddig/SPARSE_PLS
Author: Younes AJEDDIG
Author-email: younes.ajeddig@live.fr
Classifier: Programming Language :: Python :: 3
Classifier: License :: OSI Approved :: MIT License
Classifier: Operating System :: OS Independent
Requires-Python: >=3.7
License-File: LICENSE
Requires-Dist: numpy>=1.20.0
Requires-Dist: pandas>=1.2.0
Requires-Dist: scikit-learn>=0.24.0
Requires-Dist: scipy>=1.6.0
Requires-Dist: joblib>=1.0.0
Dynamic: author
Dynamic: author-email
Dynamic: classifier
Dynamic: description
Dynamic: description-content-type
Dynamic: home-page
Dynamic: requires-dist
Dynamic: requires-python
Dynamic: summary
